{"v":"5.9.6","fr":60,"ip":0,"op":232,"w":500,"h":500,"nm":"Illustration","ddd":0,"assets":[],"layers":[{"ddd":0,"ind":1,"ty":4,"nm":"Pen Outlines","sr":1,"ks":{"o":{"a":0,"k":100,"ix":11},"r":{"a":1,"k":[{"i":{"x":[0.667],"y":[1]},"o":{"x":[0.333],"y":[0]},"t":0,"s":[0]},{"i":{"x":[0.667],"y":[1]},"o":{"x":[0.333],"y":[0]},"t":22,"s":[4]},{"i":{"x":[0.667],"y":[1]},"o":{"x":[0.333],"y":[0]},"t":42,"s":[0]},{"i":{"x":[0.667],"y":[1]},"o":{"x":[0.333],"y":[0]},"t":61,"s":[4]},{"i":{"x":[0.667],"y":[1]},"o":{"x":[0.333],"y":[0]},"t":81,"s":[0]},{"i":{"x":[0.667],"y":[1]},"o":{"x":[0.333],"y":[0]},"t":109,"s":[180]},{"i":{"x":[0.667],"y":[1]},"o":{"x":[0.333],"y":[0]},"t":132,"s":[176]},{"i":{"x":[0.667],"y":[1]},"o":{"x":[0.333],"y":[0]},"t":154,"s":[180]},{"i":{"x":[0.667],"y":[1]},"o":{"x":[0.333],"y":[0]},"t":177,"s":[176]},{"i":{"x":[0.667],"y":[1]},"o":{"x":[0.333],"y":[0]},"t":199,"s":[180]},{"t":231,"s":[360]}],"ix":10},"p":{"a":0,"k":[254.024,253.441,0],"ix":2,"l":2},"a":{"a":0,"k":[81.321,92.766,0],"ix":1,"l":2},"s":{"a":0,"k":[100,100,100],"ix":6,"l":2}},"ao":0,"shapes":[{"ty":"gr","it":[{"ind":0,"ty":"sh","ix":1,"ks":{"a":0,"k":{"i":[[-0.916,-2.152],[0,0],[-0.395,1.537],[0,0],[-1.894,-1.627]],"o":[[0,0],[-1.459,0.623],[0,0],[2.266,0.581],[1.894,1.627]],"v":[[6.941,1.892],[-3.943,6.536],[-6.546,4.299],[-3.598,-7.16],[2.736,-3.873]],"c":true},"ix":2},"nm":"Path 1","mn":"ADBE Vector Shape - Group","hd":false},{"ty":"fl","c":{"a":0,"k":[0.500118031221,0.500117971383,0.500118031221,1],"ix":4},"o":{"a":0,"k":100,"ix":5},"r":1,"bm":0,"nm":"Fill 1","mn":"ADBE Vector Graphic - Fill","hd":false},{"ty":"tr","p":{"a":0,"k":[7.19,178.123],"ix":2},"a":{"a":0,"k":[0,0],"ix":1},"s":{"a":0,"k":[100,100],"ix":3},"r":{"a":0,"k":0,"ix":6},"o":{"a":0,"k":100,"ix":7},"sk":{"a":0,"k":0,"ix":4},"sa":{"a":0,"k":0,"ix":5},"nm":"Transform"}],"nm":"Group 1","np":4,"cix":2,"bm":0,"ix":1,"mn":"ADBE Vector Group","hd":false},{"ty":"gr","it":[{"ind":0,"ty":"sh","ix":1,"ks":{"a":0,"k":{"i":[[-2.602,-5.872],[0,0],[0,0],[1.894,1.627],[2.265,0.581],[0,0],[0,0],[-5.197,-4.463]],"o":[[0,0],[0,0],[-0.916,-2.153],[-1.894,-1.627],[0,0],[0,0],[6.197,1.685],[5.196,4.463]],"v":[[18.428,6.503],[17.478,7.609],[-7.89,18.435],[-12.095,12.67],[-18.428,9.383],[-11.556,-17.328],[-10.606,-18.434],[6.718,-9.233]],"c":true},"ix":2},"nm":"Path 1","mn":"ADBE Vector Shape - Group","hd":false},{"ty":"fl","c":{"a":0,"k":[0.800026448568,0.800026328891,0.800026388729,1],"ix":4},"o":{"a":0,"k":100,"ix":5},"r":1,"bm":0,"nm":"Fill 1","mn":"ADBE Vector Graphic - Fill","hd":false},{"ty":"tr","p":{"a":0,"k":[22.021,161.582],"ix":2},"a":{"a":0,"k":[0,0],"ix":1},"s":{"a":0,"k":[100,100],"ix":3},"r":{"a":0,"k":0,"ix":6},"o":{"a":0,"k":100,"ix":7},"sk":{"a":0,"k":0,"ix":4},"sa":{"a":0,"k":0,"ix":5},"nm":"Transform"}],"nm":"Group 2","np":4,"cix":2,"bm":0,"ix":2,"mn":"ADBE Vector Group","hd":false},{"ty":"gr","it":[{"ind":0,"ty":"sh","ix":1,"ks":{"a":0,"k":{"i":[[6.858,-7.984],[0,0],[5.196,4.463],[6.197,1.685],[0,0],[-7.984,-6.857]],"o":[[0,0],[-2.602,-5.872],[-5.197,-4.463],[0,0],[6.858,-7.985],[7.985,6.858]],"v":[[68.631,-50.074],[-46.454,83.917],[-58.164,68.181],[-75.488,58.98],[39.596,-75.011],[66.583,-77.06]],"c":true},"ix":2},"nm":"Path 1","mn":"ADBE Vector Shape - Group","hd":false},{"ty":"fl","c":{"a":0,"k":[0.899968644684,0.899968584846,0.899968644684,1],"ix":4},"o":{"a":0,"k":100,"ix":5},"r":1,"bm":0,"nm":"Fill 1","mn":"ADBE Vector Graphic - Fill","hd":false},{"ty":"tr","p":{"a":0,"k":[86.904,84.167],"ix":2},"a":{"a":0,"k":[0,0],"ix":1},"s":{"a":0,"k":[100,100],"ix":3},"r":{"a":0,"k":0,"ix":6},"o":{"a":0,"k":100,"ix":7},"sk":{"a":0,"k":0,"ix":4},"sa":{"a":0,"k":0,"ix":5},"nm":"Transform"}],"nm":"Group 3","np":4,"cix":2,"bm":0,"ix":3,"mn":"ADBE Vector Group","hd":false}],"ip":0,"op":1800,"st":0,"ct":1,"bm":0},{"ddd":0,"ind":2,"ty":4,"nm":"Pen Shadow Outlines","sr":1,"ks":{"o":{"a":0,"k":100,"ix":11},"r":{"a":1,"k":[{"i":{"x":[0.667],"y":[1]},"o":{"x":[0.333],"y":[0]},"t":0,"s":[0]},{"i":{"x":[0.667],"y":[1]},"o":{"x":[0.333],"y":[0]},"t":22,"s":[4]},{"i":{"x":[0.667],"y":[1]},"o":{"x":[0.333],"y":[0]},"t":42,"s":[0]},{"i":{"x":[0.667],"y":[1]},"o":{"x":[0.333],"y":[0]},"t":61,"s":[4]},{"i":{"x":[0.667],"y":[1]},"o":{"x":[0.333],"y":[0]},"t":81,"s":[0]},{"i":{"x":[0.667],"y":[1]},"o":{"x":[0.333],"y":[0]},"t":109,"s":[180]},{"i":{"x":[0.667],"y":[1]},"o":{"x":[0.333],"y":[0]},"t":132,"s":[176]},{"i":{"x":[0.667],"y":[1]},"o":{"x":[0.333],"y":[0]},"t":154,"s":[180]},{"i":{"x":[0.667],"y":[1]},"o":{"x":[0.333],"y":[0]},"t":177,"s":[176]},{"i":{"x":[0.667],"y":[1]},"o":{"x":[0.333],"y":[0]},"t":199,"s":[180]},{"t":231,"s":[360]}],"ix":10},"p":{"a":0,"k":[253.06,261.947,0],"ix":2,"l":2},"a":{"a":0,"k":[79.775,91.154,0],"ix":1,"l":2},"s":{"a":0,"k":[100,100,100],"ix":6,"l":2}},"ao":0,"shapes":[{"ty":"gr","it":[{"ind":0,"ty":"sh","ix":1,"ks":{"a":0,"k":{"i":[[7.984,6.858],[0,0],[6.858,-7.984],[0,0],[0,0],[0,0],[0,0],[-1.459,0.622],[0,0],[0,0],[0,0],[0,0]],"o":[[0,0],[-7.984,-6.858],[0,0],[0,0],[0,0],[0,0],[-0.395,1.537],[0,0],[0,0],[0,0],[0,0],[6.858,-7.985]],"v":[[73.13,-86.556],[73.13,-86.556],[46.143,-84.508],[-68.941,49.484],[-69.891,50.59],[-76.764,77.301],[-79.711,88.76],[-77.108,90.996],[-66.225,86.353],[-40.857,75.527],[-39.907,74.421],[75.177,-59.57]],"c":true},"ix":2},"nm":"Path 1","mn":"ADBE Vector Shape - Group","hd":false},{"ty":"fl","c":{"a":0,"k":[0.400130118576,0.400130088657,0.400130118576,1],"ix":4},"o":{"a":0,"k":100,"ix":5},"r":1,"bm":0,"nm":"Fill 1","mn":"ADBE Vector Graphic - Fill","hd":false},{"ty":"tr","p":{"a":0,"k":[79.775,91.154],"ix":2},"a":{"a":0,"k":[0,0],"ix":1},"s":{"a":0,"k":[100,100],"ix":3},"r":{"a":0,"k":0,"ix":6},"o":{"a":0,"k":100,"ix":7},"sk":{"a":0,"k":0,"ix":4},"sa":{"a":0,"k":0,"ix":5},"nm":"Transform"}],"nm":"Group 1","np":4,"cix":2,"bm":0,"ix":1,"mn":"ADBE Vector Group","hd":false}],"ip":0,"op":1800,"st":0,"ct":1,"bm":1},{"ddd":0,"ind":3,"ty":4,"nm":"Brush Outlines","sr":1,"ks":{"o":{"a":0,"k":100,"ix":11},"r":{"a":1,"k":[{"i":{"x":[0.667],"y":[1]},"o":{"x":[0.333],"y":[0]},"t":0,"s":[0]},{"i":{"x":[0.667],"y":[1]},"o":{"x":[0.333],"y":[0]},"t":22,"s":[-7]},{"i":{"x":[0.667],"y":[1]},"o":{"x":[0.333],"y":[0]},"t":42,"s":[0]},{"i":{"x":[0.667],"y":[1]},"o":{"x":[0.333],"y":[0]},"t":61,"s":[-7]},{"i":{"x":[0.667],"y":[1]},"o":{"x":[0.333],"y":[0]},"t":81,"s":[0]},{"i":{"x":[0.667],"y":[1]},"o":{"x":[0.333],"y":[0]},"t":109,"s":[-180]},{"i":{"x":[0.667],"y":[1]},"o":{"x":[0.333],"y":[0]},"t":132,"s":[-172]},{"i":{"x":[0.667],"y":[1]},"o":{"x":[0.333],"y":[0]},"t":154,"s":[-180]},{"i":{"x":[0.667],"y":[1]},"o":{"x":[0.333],"y":[0]},"t":177,"s":[-172]},{"i":{"x":[0.667],"y":[1]},"o":{"x":[0.333],"y":[0]},"t":199,"s":[-180]},{"t":231,"s":[-360]}],"ix":10},"p":{"a":0,"k":[248.371,253.262,0],"ix":2,"l":2},"a":{"a":0,"k":[84.205,86.64,0],"ix":1,"l":2},"s":{"a":0,"k":[100,100,100],"ix":6,"l":2}},"ao":0,"shapes":[{"ty":"gr","it":[{"ind":0,"ty":"sh","ix":1,"ks":{"a":0,"k":{"i":[[0,0],[0,0],[1.147,-1.187],[0,0],[-1.187,-1.147],[0,0]],"o":[[0,0],[-1.186,-1.147],[0,0],[-1.147,1.186],[0,0],[0,0]],"v":[[7.623,-3.122],[4.066,-6.561],[-0.177,-6.489],[-6.476,0.026],[-6.404,4.269],[-2.847,7.708]],"c":true},"ix":2},"nm":"Path 1","mn":"ADBE Vector Shape - Group","hd":false},{"ty":"fl","c":{"a":0,"k":[0.949442485735,0.949442366058,0.949442485735,1],"ix":4},"o":{"a":0,"k":100,"ix":5},"r":1,"bm":0,"nm":"Fill 1","mn":"ADBE Vector Graphic - Fill","hd":false},{"ty":"tr","p":{"a":0,"k":[36.399,45.223],"ix":2},"a":{"a":0,"k":[0,0],"ix":1},"s":{"a":0,"k":[100,100],"ix":3},"r":{"a":0,"k":0,"ix":6},"o":{"a":0,"k":100,"ix":7},"sk":{"a":0,"k":0,"ix":4},"sa":{"a":0,"k":0,"ix":5},"nm":"Transform"}],"nm":"Group 1","np":4,"cix":2,"bm":0,"ix":1,"mn":"ADBE Vector Group","hd":false},{"ty":"gr","it":[{"ind":0,"ty":"sh","ix":1,"ks":{"a":0,"k":{"i":[[-6.932,1.799],[2.143,7.109],[7.949,15.035],[0.103,-1.101],[-3.078,-5.789]],"o":[[7.187,-1.865],[-5.295,-17.563],[-0.516,-0.977],[-1.368,14.645],[4.393,8.267]],"v":[[8.659,22.429],[17.688,5.693],[-16.368,-23.252],[-18.462,-22.827],[-10.701,13.234]],"c":true},"ix":2},"nm":"Path 1","mn":"ADBE Vector Shape - Group","hd":false},{"ty":"fl","c":{"a":0,"k":[0.485783745261,0.254006718654,0.118013711069,1],"ix":4},"o":{"a":0,"k":100,"ix":5},"r":1,"bm":0,"nm":"Fill 1","mn":"ADBE Vector Graphic - Fill","hd":false},{"ty":"tr","p":{"a":0,"k":[20.08,24.479],"ix":2},"a":{"a":0,"k":[0,0],"ix":1},"s":{"a":0,"k":[100,100],"ix":3},"r":{"a":0,"k":0,"ix":6},"o":{"a":0,"k":100,"ix":7},"sk":{"a":0,"k":0,"ix":4},"sa":{"a":0,"k":0,"ix":5},"nm":"Transform"}],"nm":"Group 2","np":4,"cix":2,"bm":0,"ix":2,"mn":"ADBE Vector Group","hd":false},{"ty":"gr","it":[{"ind":0,"ty":"sh","ix":1,"ks":{"a":0,"k":{"i":[[6.629,6.409],[0,0],[10.206,-2.125],[0,0],[-3.987,-3.856],[0,0],[-6.518,6.741]],"o":[[0,0],[-3.987,-3.855],[0,0],[-2.676,10.249],[0,0],[6.629,6.408],[6.518,-6.742]],"v":[[-13.05,-36.572],[-18.679,-42.012],[-58.72,-64.408],[-65.938,-56.943],[-42.38,-17.497],[-36.751,-12.056],[62.096,59.792]],"c":true},"ix":2},"nm":"Path 1","mn":"ADBE Vector Shape - Group","hd":false},{"ty":"fl","c":{"a":0,"k":[0.004525150972,0.627506151386,0.776562559838,1],"ix":4},"o":{"a":0,"k":100,"ix":5},"r":1,"bm":0,"nm":"Fill 1","mn":"ADBE Vector Graphic - Fill","hd":false},{"ty":"tr","p":{"a":0,"k":[99.546,106.496],"ix":2},"a":{"a":0,"k":[0,0],"ix":1},"s":{"a":0,"k":[100,100],"ix":3},"r":{"a":0,"k":0,"ix":6},"o":{"a":0,"k":100,"ix":7},"sk":{"a":0,"k":0,"ix":4},"sa":{"a":0,"k":0,"ix":5},"nm":"Transform"}],"nm":"Group 3","np":4,"cix":2,"bm":0,"ix":3,"mn":"ADBE Vector Group","hd":false}],"ip":0,"op":1800,"st":0,"ct":1,"bm":0},{"ddd":0,"ind":4,"ty":4,"nm":"Brush Shadow Outlines","sr":1,"ks":{"o":{"a":0,"k":100,"ix":11},"r":{"a":1,"k":[{"i":{"x":[0.667],"y":[1]},"o":{"x":[0.333],"y":[0]},"t":0,"s":[0]},{"i":{"x":[0.667],"y":[1]},"o":{"x":[0.333],"y":[0]},"t":22,"s":[-7]},{"i":{"x":[0.667],"y":[1]},"o":{"x":[0.333],"y":[0]},"t":42,"s":[0]},{"i":{"x":[0.667],"y":[1]},"o":{"x":[0.333],"y":[0]},"t":61,"s":[-7]},{"i":{"x":[0.667],"y":[1]},"o":{"x":[0.333],"y":[0]},"t":81,"s":[0]},{"i":{"x":[0.667],"y":[1]},"o":{"x":[0.333],"y":[0]},"t":109,"s":[-180]},{"i":{"x":[0.667],"y":[1]},"o":{"x":[0.333],"y":[0]},"t":132,"s":[-172]},{"i":{"x":[0.667],"y":[1]},"o":{"x":[0.333],"y":[0]},"t":154,"s":[-180]},{"i":{"x":[0.667],"y":[1]},"o":{"x":[0.333],"y":[0]},"t":177,"s":[-172]},{"i":{"x":[0.667],"y":[1]},"o":{"x":[0.333],"y":[0]},"t":199,"s":[-180]},{"t":231,"s":[-360]}],"ix":10},"p":{"a":0,"k":[245.898,256.374,0],"ix":2,"l":2},"a":{"a":0,"k":[80.311,83.048,0],"ix":1,"l":2},"s":{"a":0,"k":[100,100,100],"ix":6,"l":2}},"ao":0,"shapes":[{"ty":"gr","it":[{"ind":0,"ty":"sh","ix":1,"ks":{"a":0,"k":{"i":[[6.629,6.409],[0,0],[11.58,1.533],[0,0],[1.17,-0.216],[0.818,2.712],[7.95,15.034],[0.103,-1.101],[-3.077,-5.789],[-6.932,1.799],[-0.244,0.079],[-0.934,-0.902],[0,0],[-3.607,-3.488],[0,0],[-6.518,6.741]],"o":[[0,0],[-3.625,-3.505],[0,0],[-0.915,-0.885],[0.804,-2.538],[-5.294,-17.562],[-0.516,-0.977],[-1.369,14.646],[4.393,8.266],[0.252,-0.066],[-0.202,1.197],[0,0],[1.526,11.576],[0,0],[6.629,6.408],[6.518,-6.742]],"v":[[4.764,-13.76],[-0.865,-19.201],[-37.766,-41.637],[-40.69,-44.464],[-44.03,-45.457],[-43.964,-53.513],[-78.02,-82.457],[-80.113,-82.034],[-72.352,-45.972],[-52.993,-36.776],[-52.259,-37.01],[-51.159,-33.635],[-48.244,-30.816],[-24.566,5.315],[-18.937,10.756],[79.91,82.604]],"c":true},"ix":2},"nm":"Path 1","mn":"ADBE Vector Shape - Group","hd":false},{"ty":"fl","c":{"a":0,"k":[0.400130118576,0.400130088657,0.400130118576,1],"ix":4},"o":{"a":0,"k":100,"ix":5},"r":1,"bm":0,"nm":"Fill 1","mn":"ADBE Vector Graphic - Fill","hd":false},{"ty":"tr","p":{"a":0,"k":[80.311,83.048],"ix":2},"a":{"a":0,"k":[0,0],"ix":1},"s":{"a":0,"k":[100,100],"ix":3},"r":{"a":0,"k":0,"ix":6},"o":{"a":0,"k":100,"ix":7},"sk":{"a":0,"k":0,"ix":4},"sa":{"a":0,"k":0,"ix":5},"nm":"Transform"}],"nm":"Group 1","np":4,"cix":2,"bm":0,"ix":1,"mn":"ADBE Vector Group","hd":false}],"ip":0,"op":1800,"st":0,"ct":1,"bm":0},{"ddd":0,"ind":5,"ty":4,"nm":"iPad Outlines","sr":1,"ks":{"o":{"a":0,"k":100,"ix":11},"r":{"a":1,"k":[{"i":{"x":[0.667],"y":[1]},"o":{"x":[0.333],"y":[0]},"t":0,"s":[0]},{"i":{"x":[0.667],"y":[1]},"o":{"x":[0.333],"y":[0]},"t":74,"s":[6]},{"i":{"x":[0.667],"y":[1]},"o":{"x":[0.333],"y":[0]},"t":153,"s":[-6]},{"t":231,"s":[0]}],"ix":10},"p":{"a":0,"k":[252.946,254.2,0],"ix":2,"l":2},"a":{"a":0,"k":[143.07,183.905,0],"ix":1,"l":2},"s":{"a":0,"k":[100,100,100],"ix":6,"l":2}},"ao":0,"shapes":[{"ty":"gr","it":[{"ind":0,"ty":"sh","ix":1,"ks":{"a":0,"k":{"i":[[0,0],[0,0],[0,1.389],[0,0],[1.389,-0.001],[0,0]],"o":[[0,0],[1.389,0],[0,0],[0,-1.389],[0,0],[0,0]],"v":[[-1.734,17.529],[-0.775,17.529],[1.741,15.014],[1.736,-15.014],[-0.78,-17.528],[-1.741,-17.528]],"c":true},"ix":2},"nm":"Path 1","mn":"ADBE Vector Shape - Group","hd":false},{"ty":"fl","c":{"a":0,"k":[0.182165811576,0.344603594612,0.6491496965,1],"ix":4},"o":{"a":0,"k":100,"ix":5},"r":1,"bm":0,"nm":"Fill 1","mn":"ADBE Vector Graphic - Fill","hd":false},{"ty":"tr","p":{"a":0,"k":[282.322,115.409],"ix":2},"a":{"a":0,"k":[0,0],"ix":1},"s":{"a":0,"k":[100,100],"ix":3},"r":{"a":0,"k":0,"ix":6},"o":{"a":0,"k":100,"ix":7},"sk":{"a":0,"k":0,"ix":4},"sa":{"a":0,"k":0,"ix":5},"nm":"Transform"}],"nm":"Group 1","np":4,"cix":2,"bm":0,"ix":1,"mn":"ADBE Vector Group","hd":false},{"ty":"gr","it":[{"ind":0,"ty":"sh","ix":1,"ks":{"a":0,"k":{"i":[[0,0],[0,0],[1.919,0],[0,0],[-0.001,-1.761]],"o":[[0,0],[0,-1.761],[0,0],[-1.919,0],[0,0]],"v":[[14.853,1.592],[14.853,1.592],[11.376,-1.596],[-11.378,-1.593],[-14.852,1.596]],"c":true},"ix":2},"nm":"Path 1","mn":"ADBE Vector Shape - Group","hd":false},{"ty":"fl","c":{"a":0,"k":[0.182165811576,0.344603594612,0.6491496965,1],"ix":4},"o":{"a":0,"k":100,"ix":5},"r":1,"bm":0,"nm":"Fill 1","mn":"ADBE Vector Graphic - Fill","hd":false},{"ty":"tr","p":{"a":0,"k":[221.698,1.846],"ix":2},"a":{"a":0,"k":[0,0],"ix":1},"s":{"a":0,"k":[100,100],"ix":3},"r":{"a":0,"k":0,"ix":6},"o":{"a":0,"k":100,"ix":7},"sk":{"a":0,"k":0,"ix":4},"sa":{"a":0,"k":0,"ix":5},"nm":"Transform"}],"nm":"Group 2","np":4,"cix":2,"bm":0,"ix":2,"mn":"ADBE Vector Group","hd":false},{"ty":"gr","it":[{"ind":0,"ty":"sh","ix":1,"ks":{"a":0,"k":{"i":[[0,0],[0,0],[0,1.389],[0,0],[1.389,0],[0,0]],"o":[[0,0],[1.389,0],[0,0],[-0.001,-1.389],[0,0],[0,0]],"v":[[-1.734,17.529],[-0.774,17.529],[1.74,15.014],[1.735,-15.014],[-0.781,-17.529],[-1.74,-17.529]],"c":true},"ix":2},"nm":"Path 1","mn":"ADBE Vector Shape - Group","hd":false},{"ty":"fl","c":{"a":0,"k":[0.182165811576,0.344603594612,0.6491496965,1],"ix":4},"o":{"a":0,"k":100,"ix":5},"r":1,"bm":0,"nm":"Fill 1","mn":"ADBE Vector Graphic - Fill","hd":false},{"ty":"tr","p":{"a":0,"k":[282.32,78.412],"ix":2},"a":{"a":0,"k":[0,0],"ix":1},"s":{"a":0,"k":[100,100],"ix":3},"r":{"a":0,"k":0,"ix":6},"o":{"a":0,"k":100,"ix":7},"sk":{"a":0,"k":0,"ix":4},"sa":{"a":0,"k":0,"ix":5},"nm":"Transform"}],"nm":"Group 3","np":4,"cix":2,"bm":0,"ix":3,"mn":"ADBE Vector Group","hd":false},{"ty":"gr","it":[{"ind":0,"ty":"sh","ix":1,"ks":{"a":0,"k":{"i":[[15.592,-0.002],[0,0],[0.003,15.59],[0,0],[-15.592,0.002],[0,0],[-0.002,-15.59],[0,0]],"o":[[0,0],[-15.592,0.003],[0,0],[-0.002,-15.592],[0,0],[15.591,-0.002],[0,0],[0.003,15.592]],"v":[[88.588,157.198],[-88.538,157.221],[-116.891,128.879],[-116.932,-128.845],[-88.587,-157.198],[88.538,-157.222],[116.89,-128.879],[116.932,128.845]],"c":true},"ix":2},"nm":"Path 1","mn":"ADBE Vector Shape - Group","hd":false},{"ty":"fl","c":{"a":0,"k":[0.999999880323,0.999999820485,0.999999880323,1],"ix":4},"o":{"a":0,"k":100,"ix":5},"r":1,"bm":0,"nm":"Fill 1","mn":"ADBE Vector Graphic - Fill","hd":false},{"ty":"tr","p":{"a":0,"k":[137.267,180.173],"ix":2},"a":{"a":0,"k":[0,0],"ix":1},"s":{"a":0,"k":[100,100],"ix":3},"r":{"a":0,"k":0,"ix":6},"o":{"a":0,"k":100,"ix":7},"sk":{"a":0,"k":0,"ix":4},"sa":{"a":0,"k":0,"ix":5},"nm":"Transform"}],"nm":"Group 4","np":4,"cix":2,"bm":0,"ix":4,"mn":"ADBE Vector Group","hd":false},{"ty":"gr","it":[{"ind":0,"ty":"sh","ix":1,"ks":{"a":0,"k":{"i":[[15.592,-0.002],[0,0],[0.003,15.59],[0,0],[-15.592,0.002],[0,0],[-0.003,-15.591],[0,0]],"o":[[0,0],[-15.591,0.003],[0,0],[-0.002,-15.592],[0,0],[15.591,-0.003],[0,0],[0.003,15.592]],"v":[[108.671,176.708],[-108.616,176.737],[-136.968,148.395],[-137.015,-148.355],[-108.671,-176.708],[108.615,-176.737],[136.967,-148.394],[137.014,148.355]],"c":true},"ix":2},"nm":"Path 1","mn":"ADBE Vector Shape - Group","hd":false},{"ty":"fl","c":{"a":0,"k":[0.182165811576,0.344603594612,0.6491496965,1],"ix":4},"o":{"a":0,"k":100,"ix":5},"r":1,"bm":0,"nm":"Fill 1","mn":"ADBE Vector Graphic - Fill","hd":false},{"ty":"tr","p":{"a":0,"k":[137.267,180.172],"ix":2},"a":{"a":0,"k":[0,0],"ix":1},"s":{"a":0,"k":[100,100],"ix":3},"r":{"a":0,"k":0,"ix":6},"o":{"a":0,"k":100,"ix":7},"sk":{"a":0,"k":0,"ix":4},"sa":{"a":0,"k":0,"ix":5},"nm":"Transform"}],"nm":"Group 5","np":4,"cix":2,"bm":0,"ix":5,"mn":"ADBE Vector Group","hd":false},{"ty":"gr","it":[{"ind":0,"ty":"sh","ix":1,"ks":{"a":0,"k":{"i":[[15.593,-0.002],[0,0],[0.002,15.591],[0,0],[-15.592,0.003],[0,0],[-0.003,-15.591],[0,0]],"o":[[0,0],[-15.591,0.002],[0,0],[-0.002,-15.593],[0,0],[15.591,-0.003],[0,0],[0.003,15.592]],"v":[[108.67,176.708],[-108.616,176.738],[-136.968,148.394],[-137.016,-148.354],[-108.671,-176.708],[108.615,-176.736],[136.968,-148.393],[137.015,148.355]],"c":true},"ix":2},"nm":"Path 1","mn":"ADBE Vector Shape - Group","hd":false},{"ty":"fl","c":{"a":0,"k":[0.047743464451,0.064523973652,0.295772537531,1],"ix":4},"o":{"a":0,"k":100,"ix":5},"r":1,"bm":0,"nm":"Fill 1","mn":"ADBE Vector Graphic - Fill","hd":false},{"ty":"tr","p":{"a":0,"k":[148.872,190.821],"ix":2},"a":{"a":0,"k":[0,0],"ix":1},"s":{"a":0,"k":[100,100],"ix":3},"r":{"a":0,"k":0,"ix":6},"o":{"a":0,"k":100,"ix":7},"sk":{"a":0,"k":0,"ix":4},"sa":{"a":0,"k":0,"ix":5},"nm":"Transform"}],"nm":"Group 6","np":4,"cix":2,"bm":0,"ix":6,"mn":"ADBE Vector Group","hd":false}],"ip":0,"op":1800,"st":0,"ct":1,"bm":0}],"markers":[]}